apartment_browser/__init__.py
apartment_browser/addons.py
apartment_browser/routes.py
apartment_browser/server.py
apartment_browser/settings.py
apartment_browser/coreutils/__init__.py
apartment_browser/coreutils/exceptions.py
apartment_browser/coreutils/middlewares.py
apartment_browser/coreutils/service.py
apartment_browser/domain/__init__.py
apartment_browser/domain/apartment/__init__.py
apartment_browser/domain/apartment/endpoints.py
apartment_browser/domain/apartment/schemas.py
apartment_browser/domain/apartment/services.py
apartment_browser/domain/bookmark/__init__.py
apartment_browser/domain/bookmark/endpoints.py
apartment_browser/domain/bookmark/schemas.py
apartment_browser/domain/bookmark/services.py
apartment_browser-0.0.1.dist-info/METADATA
apartment_browser-0.0.1.dist-info/WHEEL
apartment_browser-0.0.1.dist-info/top_level.txt
apartment_browser-0.0.1.dist-info/RECORD
