Metadata-Version: 2.1
Name: apartment-browser
Version: 0.0.1
Summary: Backend used by "apartment browser" web extensions
Home-page: UNKNOWN
Author: UNKNOWN
Author-email: UNKNOWN
License: UNKNOWN
Platform: UNKNOWN
Requires-Dist: aiofiles (==0.6.0)
Requires-Dist: certifi (==2020.11.8)
Requires-Dist: click (==7.1.2)
Requires-Dist: gunicorn (==20.0.4)
Requires-Dist: h11 (==0.9.0)
Requires-Dist: httpcore (==0.11.1)
Requires-Dist: httptools (==0.1.1)
Requires-Dist: httpx (==0.15.4)
Requires-Dist: idna (==2.10)
Requires-Dist: marshmallow (==3.9.1)
Requires-Dist: multidict (==5.0.0)
Requires-Dist: pymongo (==3.11.0)
Requires-Dist: rfc3986[idna2008] (==1.4.0)
Requires-Dist: sanic (==20.9.1)
Requires-Dist: sniffio (==1.2.0)
Requires-Dist: ujson (==4.0.1)
Requires-Dist: uvicorn (==0.12.2)
Requires-Dist: uvloop (==0.14.0)
Requires-Dist: websockets (==8.1)
